ClasseVivaAPI/__init__.py
ClasseVivaAPI/classeviva.py
CVV_API-0.1.dist-info/METADATA
CVV_API-0.1.dist-info/WHEEL
CVV_API-0.1.dist-info/top_level.txt
CVV_API-0.1.dist-info/RECORD
