Metadata-Version: 2.1
Name: CVV-API
Version: 0.1
Summary: ClasseViva-API è una libreria Python che permette di utlizzare l'API di Classeviva - GruppoSpaggiariParma per ottenere informazioni come Voti, Note e Documenti, relative ad un account ClasseViva.
Home-page: https://github.com/MakerFaffa/ClasseVivaAPI
Author: Fabrizio Gasparini
Author-email: gasparini.fabrizio@einaudicorreggio.it
Keywords: classeviva,api,ClasseViva-API
Classifier: Programming Language :: Python :: 3
Requires-Python: >=3.10
Requires-Dist: requests
